ipython_reverser/__init__.py
IPythonReverser-0.1.dist-info/LICENSE
IPythonReverser-0.1.dist-info/METADATA
IPythonReverser-0.1.dist-info/WHEEL
IPythonReverser-0.1.dist-info/top_level.txt
IPythonReverser-0.1.dist-info/RECORD
