Metadata-Version: 2.1
Name: IPythonReverser
Version: 0.1
Summary: IPython magic to reverse a string
Home-page: http://www.github.com/switowski/ipython-reverser
Author: Sebastian Witowski
Author-email: sebastian@switowski.com
License: MIT
Keywords: ipython reverser reverse
Platform: UNKNOWN
Classifier: Development Status :: 3 - Alpha
Classifier: Intended Audience :: Developers
Classifier: Framework :: IPython
Classifier: Programming Language :: Python
Classifier: Topic :: Utilities
Requires-Dist: ipython
